nostr_bots/__about__.py
nostr_bots/__init__.py
nostr_bots/acceptors.py
nostr_bots/basic.py
nostr_bots/bitcoind.py
nostr_bots/run_bitcoin_bot.py
nostr_bots/run_echo_bot.py
nostr_bots/run_ip_bot.py
nostr_bots/util.py
nostr_bots-0.0.4.dist-info/METADATA
nostr_bots-0.0.4.dist-info/WHEEL
nostr_bots-0.0.4.dist-info/licenses/LICENSE.txt
nostr_bots-0.0.4.dist-info/RECORD
