Metadata-Version: 2.3
Name: nostr_bots
Version: 0.0.4
Summary: simple bots for nostr using monstr
Project-URL: Documentation, https://github.com/monty888/nostr_bots#readme
Project-URL: Issues, https://github.com/monty888/nostr_bots/issues
Project-URL: Source, https://github.com/monty888/nostr_bots
Author-email: monty <monty@monty888.com>
License-Expression: MIT
License-File: LICENSE.txt
Classifier: Development Status :: 4 - Beta
Classifier: Programming Language :: Python :: 3.10
Classifier: Programming Language :: Python :: 3.11
Classifier: Programming Language :: Python :: 3.12
Classifier: Programming Language :: Python :: Implementation :: CPython
Classifier: Programming Language :: Python :: Implementation :: PyPy
Requires-Python: >=3.10
Requires-Dist: monstr>=0.1.2
